setup.py
twitchobserver/__init__.py
twitchobserver/twitchobserver.py
twitchobserver.egg-info/PKG-INFO
twitchobserver.egg-info/SOURCES.txt
twitchobserver.egg-info/dependency_links.txt
twitchobserver.egg-info/top_level.txt